{
  "branch_summaries": [
    {
      "atoms_with_one_feature_hit": 7,
      "atoms_with_two_feature_hit": 1,
      "branch": "R42-even-q",
      "new_two_feature_atom": "13->4|L1|B6:6|R0:0",
      "new_two_feature_j_values": [
        0,
        2,
        4,
        6,
        8,
        10
      ],
      "q_values": [
        6,
        8,
        10
      ],
      "rows": 222,
      "unresolved_atom": "20->26|L1|B7:7|R0:0",
      "unresolved_j_values": [
        0,
        1,
        2,
        3,
        4,
        5,
        6,
        7,
        8,
        9,
        10
      ]
    },
    {
      "atoms_with_one_feature_hit": 7,
      "atoms_with_two_feature_hit": 1,
      "branch": "R42-odd-q",
      "new_two_feature_atom": "13->4|L1|B6:6|R0:0",
      "new_two_feature_j_values": [
        0,
        2,
        4,
        6,
        8,
        10
      ],
      "q_values": [
        7,
        9,
        11
      ],
      "rows": 246,
      "unresolved_atom": "20->26|L1|B7:7|R0:0",
      "unresolved_j_values": [
        0,
        1,
        2,
        3,
        4,
        5,
        6,
        7,
        8,
        9,
        10,
        11
      ]
    }
  ],
  "diagnostic_result": {
    "bad_atom_count_per_branch": 9,
    "new_two_feature_atom": "13->4|L1|B6:6|R0:0",
    "one_feature_hits_per_branch": {
      "R42-even-q": 7,
      "R42-odd-q": 7
    },
    "simple_one_or_two_feature_schema_stable": false,
    "two_feature_hits_per_branch": {
      "R42-even-q": 1,
      "R42-odd-q": 1
    },
    "unresolved_atom": "20->26|L1|B7:7|R0:0"
  },
  "error_count": 0,
  "errors": [],
  "even_artifact": "/data/angel/repos/etc/Torus-Hamilton-Decomposition-Program/certs/routeE_r42_bad_intercept_carry_split_even_q6_8_10.json",
  "odd_artifact": "/data/angel/repos/etc/Torus-Hamilton-Decomposition-Program/certs/routeE_r42_bad_intercept_carry_split_odd_q7_9_11.json",
  "ok": true,
  "promotion_impact": {
    "closes_residue": false,
    "diagnosis": "Adding q=10 and q=11 breaks the apparent two-sample split: one atom remains unresolved even with all tested one/two features.  R42 may still have a deeper clock-carry structure, but the one-step carry split is not a branch theorem.",
    "no_early_closed": false,
    "pointwise_equations_closed": false,
    "refutes_simple_one_step_carry_split": true
  },
  "schema": "routeE_r42_bad_intercept_carry_split_stress_verification_v1"
}
